flask_scotch/LocalModel.py
flask_scotch/LocalRelationship.py
flask_scotch/RemoteModel.py
flask_scotch/RemoteRelationship.py
flask_scotch/__init__.py
flask_scotch/utils.py
flask_scotch-0.0.2.dist-info/LICENSE
flask_scotch-0.0.2.dist-info/METADATA
flask_scotch-0.0.2.dist-info/WHEEL
flask_scotch-0.0.2.dist-info/top_level.txt
flask_scotch-0.0.2.dist-info/RECORD
