Metadata-Version: 2.1
Name: flask-scotch
Version: 0.0.2
Summary: Tape a REST API with a local database
Home-page: https://github.com/AzariasB/flask-scotch
Author: AzariasB
Maintainer: AzariasB
License: MIT
Platform: any
Classifier: Intended Audience :: Developers
Classifier: License :: OSI Approved :: MIT License
Classifier: Operating System :: OS Independent
Classifier: Programming Language :: Python
Classifier: Programming Language :: Python :: 3
Classifier: Programming Language :: Python :: 3 :: Only
Classifier: Programming Language :: Python :: 3.9
Classifier: Programming Language :: Python :: Implementation :: CPython
Classifier: Topic :: Software Development :: Libraries :: Python Modules
Classifier: Topic :: Software Development
Classifier: Topic :: Database
Requires-Python: >=3.9
License-File: LICENSE
Requires-Dist: Flask (>=2.0.1)
Requires-Dist: SQLAlchemy (>=1.4.18)
Requires-Dist: pydantic (>=1.8.2)
Requires-Dist: requests (>=2.26.0)
